<?xml version="1.0" encoding="utf-8"?>
<aurora>
    <ret_code>0</ret_code>
    <ret_msg>success</ret_msg>
    <data><page>1</page>
<page_size>5</page_size>
<page_total>1</page_total>
<target_total>5</target_total>
<report>
<vendor>绿盟科技</vendor>
<product>网络安全漏洞扫描系统</product>
<version>V6.0R04F04SP08</version><sysvul_version>V6.0R02F01.4307</sysvul_version>
<vultpl_version>V6.0R04F01.0000</vultpl_version>

<task>
<id>1223</id>
<name><![CDATA[扫描【12考核弱口令】]]></name>
<task_type>4</task_type>

<time_start_scan>2025-12-18 15:31:16</time_start_scan>
<time_end_scan>2025-12-18 15:37:56</time_end_scan>
</task>
<scanned_ip_count>5</scanned_ip_count>
<failed_hosts>

</failed_hosts>



<targets>

<target>
<ip>172.30.3.36</ip>
<host_score>5.1</host_score>

<vul_score>5.1</vul_score>


<config_score>0</config_score>







<vuln_scanned>

<vuln>
<port>22</port>
<vul_id>2012</vul_id>
<protocol>TCP</protocol>
<service>ssh</service>
<mess_string><![CDATA[ssh [admin:admin]\nssh [test:test]\nssh [user:user]]]></mess_string>
<vul_confirmed>False</vul_confirmed>
<has_result>-1</has_result>


</vuln>

<vuln>
<port>22</port>
<vul_id>2057</vul_id>
<protocol>TCP</protocol>
<service>ssh</service>
<mess_string><![CDATA[sftp [admin:admin]\nsftp [test:test]\nsftp [user:user]]]></mess_string>
<vul_confirmed>False</vul_confirmed>
<has_result>-1</has_result>


</vuln>

<vuln>
<port>3306</port>
<vul_id>2009</vul_id>
<protocol>TCP</protocol>
<service>mysql</service>
<mess_string><![CDATA[mysql [root:root]]]></mess_string>
<vul_confirmed>False</vul_confirmed>
<has_result>-1</has_result>


</vuln>

</vuln_scanned>



<vuln_detail>

<vuln>
<vul_id>2009</vul_id>
<plugin_id>2009</plugin_id>


<name>猜测出远程MySQL数据库服务存在可登录的用户名口令</name>

<threat_category>远程信息泄露</threat_category>
<cve_id></cve_id>
<nsfocus_id></nsfocus_id>
<bugtraq_id></bugtraq_id>
<cnnvd></cnnvd>
<cncve></cncve>
<date_found>2001-01-01</date_found>
<risk_points>5.0</risk_points>
<solution><![CDATA[建议您采取以下措施以降低威胁:

* 修改用户口令:设置足够强度的口令。

* 经常查看MySQL的漏洞情况,及时安装其更新升级包]]></solution>

<description><![CDATA[本次扫描通过暴力猜测方式证实目标主机上的MySQL数据库服务存在可猜测的口令。

远程攻击者可通过猜测出的用户名口令对目标主机实施进一步的攻击，这将极大地威胁目标主机以及目标网络的安全。]]></description>
</vuln>

<vuln>
<vul_id>2012</vul_id>
<plugin_id>2012</plugin_id>


<name>猜测出远程SSH服务存在用户名口令</name>

<threat_category>远程信息泄露</threat_category>
<cve_id></cve_id>
<nsfocus_id></nsfocus_id>
<bugtraq_id></bugtraq_id>
<cnnvd></cnnvd>
<cncve></cncve>
<date_found>2001-01-01</date_found>
<risk_points>5.0</risk_points>
<solution><![CDATA[建议您采取以下措施以降低威胁:

* 如果SSH服务不是必须的，建议停止此服务。

* 修改用户口令，设置足够强度的口令。]]></solution>

<description><![CDATA[本次扫描通过暴力猜测方式证实目标主机上的SSH服务存在可猜测的口令。

远程攻击者可通过猜测出的用户名口令对目标主机实施进一步的攻击，这将极大地威胁目标主机以及目标网络的安全。]]></description>
</vuln>

<vuln>
<vul_id>2057</vul_id>
<plugin_id>2057</plugin_id>


<name>猜测出sftp存在可登录的用户名口令</name>

<threat_category>远程信息泄露</threat_category>
<cve_id></cve_id>
<nsfocus_id></nsfocus_id>
<bugtraq_id></bugtraq_id>
<cnnvd></cnnvd>
<cncve></cncve>
<date_found>2021-05-24</date_found>
<risk_points>5.0</risk_points>
<solution><![CDATA[建议您采取以下措施以降低威胁:
修改用户口令:设置足够强度的口令。]]></solution>

<description><![CDATA[本次扫描通过暴力猜测方式证实sftp存在可登录的口令。远程攻击者可通过猜测出的用户名口令对目标主机实施进一步的攻击，这将极大地威胁目标主机以及目标网络的安全。]]></description>
</vuln>

</vuln_detail>





<password_results>

<password_result>
<type>SSH</type>
<username>test</username>
<password>test</password>
</password_result>

<password_result>
<type>SFTP</type>
<username>admin</username>
<password>admin</password>
</password_result>

<password_result>
<type>MySQL</type>
<username>root</username>
<password>root</password>
</password_result>

<password_result>
<type>SSH</type>
<username>admin</username>
<password>admin</password>
</password_result>

<password_result>
<type>SFTP</type>
<username>user</username>
<password>user</password>
</password_result>

<password_result>
<type>SFTP</type>
<username>test</username>
<password>test</password>
</password_result>

<password_result>
<type>SSH</type>
<username>user</username>
<password>user</password>
</password_result>

</password_results>


<appendix_info>

<info>
<info_name><![CDATA[操作系统类型]]></info_name>
<record_result_name>

<name><![CDATA[操作系统名字]]></name>

<name><![CDATA[版本号]]></name>

</record_result_name>

<record_results>
<result>

<value><![CDATA[$1]]></value>

<value><![CDATA[]]></value>

</result>
</record_results>

<record_results/>
</info>

<info>
<info_name><![CDATA[端口Banner]]></info_name>
<record_result_name>

<name><![CDATA[端口]]></name>

<name><![CDATA[Banner]]></name>

</record_result_name>

<record_results>
<result>

<value><![CDATA[8080]]></value>

<value><![CDATA[Jetty/9.4.27.v20200227]]></value>

</result>
</record_results>

<record_results>
<result>

<value><![CDATA[3306]]></value>

<value><![CDATA[MySQL/5.7.44]]></value>

</result>
</record_results>

<record_results>
<result>

<value><![CDATA[8888]]></value>

<value><![CDATA[Apache httpd/2.4.61]]></value>

</result>
</record_results>

<record_results>
<result>

<value><![CDATA[8086]]></value>

<value><![CDATA[Apache Tomcat/8.0.53]]></value>

</result>
</record_results>

<record_results>
<result>

<value><![CDATA[8086]]></value>

<value><![CDATA[Apache Tomcat/Coyote JSP engine/1.1]]></value>

</result>
</record_results>

<record_results>
<result>

<value><![CDATA[8081]]></value>

<value><![CDATA[Apache httpd/2.4.62]]></value>

</result>
</record_results>

<record_results>
<result>

<value><![CDATA[22]]></value>

<value><![CDATA[OpenSSH/7.4]]></value>

</result>
</record_results>

<record_results>
<result>

<value><![CDATA[443]]></value>

<value><![CDATA[php/5.3.10-1ubuntu3.26 php]]></value>

</result>
</record_results>

<record_results>
<result>

<value><![CDATA[443]]></value>

<value><![CDATA[Apache httpd/2.2.22]]></value>

</result>
</record_results>

<record_results>
<result>

<value><![CDATA[6379]]></value>

<value><![CDATA[Redis key-value store/6.2.16]]></value>

</result>
</record_results>

<record_results>
<result>

<value><![CDATA[8086]]></value>

<value><![CDATA[Tomcat/8.0.53]]></value>

</result>
</record_results>

<record_results>
<result>

<value><![CDATA[443]]></value>

<value><![CDATA[Apache/2.2.22 (Ubuntu);PHP/5.3.10-1ubuntu3.26]]></value>

</result>
</record_results>

<record_results>
<result>

<value><![CDATA[3306]]></value>

<value><![CDATA[MySQL Server MySQL/5.7.44]]></value>

</result>
</record_results>

<record_results/>
</info>

<info>
<info_name><![CDATA[远程端口信息]]></info_name>
<record_result_name>

<name><![CDATA[端口]]></name>

<name><![CDATA[协议]]></name>

<name><![CDATA[服务]]></name>

<name><![CDATA[状态]]></name>

</record_result_name>

<record_results>
<result>

<value><![CDATA[22]]></value>

<value><![CDATA[tcp]]></value>

<value><![CDATA[ssh]]></value>

<value><![CDATA[open]]></value>

</result>
</record_results>

<record_results>
<result>

<value><![CDATA[443]]></value>

<value><![CDATA[tcp]]></value>

<value><![CDATA[HTTPS]]></value>

<value><![CDATA[open]]></value>

</result>
</record_results>

<record_results>
<result>

<value><![CDATA[8080-8081]]></value>

<value><![CDATA[tcp]]></value>

<value><![CDATA[http]]></value>

<value><![CDATA[open]]></value>

</result>
</record_results>

<record_results>
<result>

<value><![CDATA[8888]]></value>

<value><![CDATA[tcp]]></value>

<value><![CDATA[http]]></value>

<value><![CDATA[open]]></value>

</result>
</record_results>

<record_results>
<result>

<value><![CDATA[8086]]></value>

<value><![CDATA[tcp]]></value>

<value><![CDATA[www]]></value>

<value><![CDATA[open]]></value>

</result>
</record_results>

<record_results>
<result>

<value><![CDATA[6379]]></value>

<value><![CDATA[tcp]]></value>

<value><![CDATA[redis]]></value>

<value><![CDATA[open]]></value>

</result>
</record_results>

<record_results>
<result>

<value><![CDATA[3306]]></value>

<value><![CDATA[tcp]]></value>

<value><![CDATA[MySQL]]></value>

<value><![CDATA[open]]></value>

</result>
</record_results>

<record_results/>
</info>

<info>
<info_name><![CDATA[安装软件信息]]></info_name>
<record_result_name>

<name><![CDATA[软件名称]]></name>

<name><![CDATA[版本号]]></name>

</record_result_name>

<record_results>
<result>

<value><![CDATA[WWW]]></value>

<value><![CDATA[Tomcat]]></value>

</result>
</record_results>

<record_results>
<result>

<value><![CDATA[Tomcat]]></value>

<value><![CDATA[8.0.53]]></value>

</result>
</record_results>

<record_results>
<result>

<value><![CDATA[OpenSSH]]></value>

<value><![CDATA[7.4]]></value>

</result>
</record_results>

<record_results>
<result>

<value><![CDATA[Jetty]]></value>

<value><![CDATA[9.4.27.v20200227]]></value>

</result>
</record_results>

<record_results>
<result>

<value><![CDATA[Apache httpd]]></value>

<value><![CDATA[2.4.61]]></value>

</result>
</record_results>

<record_results>
<result>

<value><![CDATA[HTTPS]]></value>

<value><![CDATA[Apache]]></value>

</result>
</record_results>

<record_results>
<result>

<value><![CDATA[Apache Tomcat]]></value>

<value><![CDATA[8.0.53]]></value>

</result>
</record_results>

<record_results>
<result>

<value><![CDATA[Redis key-value store]]></value>

<value><![CDATA[6.2.16]]></value>

</result>
</record_results>

<record_results>
<result>

<value><![CDATA[php]]></value>

<value><![CDATA[5.3.10-1ubuntu3.26 php]]></value>

</result>
</record_results>

<record_results>
<result>

<value><![CDATA[MySQL]]></value>

<value><![CDATA[MySQL/5.7.44]]></value>

</result>
</record_results>

<record_results/>
</info>

<info>
<info_name><![CDATA[应用程序信息]]></info_name>
<record_result_name>

<name><![CDATA[用户名]]></name>

<name><![CDATA[口令]]></name>

<name><![CDATA[应用]]></name>

</record_result_name>

<record_results>
<result>

<value><![CDATA[test]]></value>

<value><![CDATA[test]]></value>

<value><![CDATA[SSH]]></value>

<value><![CDATA[22]]></value>

</result>
</record_results>

<record_results>
<result>

<value><![CDATA[admin]]></value>

<value><![CDATA[admin]]></value>

<value><![CDATA[SFTP]]></value>

<value><![CDATA[22]]></value>

</result>
</record_results>

<record_results>
<result>

<value><![CDATA[root]]></value>

<value><![CDATA[root]]></value>

<value><![CDATA[MySQL]]></value>

<value><![CDATA[3306]]></value>

</result>
</record_results>

<record_results>
<result>

<value><![CDATA[admin]]></value>

<value><![CDATA[admin]]></value>

<value><![CDATA[SSH]]></value>

<value><![CDATA[22]]></value>

</result>
</record_results>

<record_results>
<result>

<value><![CDATA[user]]></value>

<value><![CDATA[user]]></value>

<value><![CDATA[SFTP]]></value>

<value><![CDATA[22]]></value>

</result>
</record_results>

<record_results>
<result>

<value><![CDATA[test]]></value>

<value><![CDATA[test]]></value>

<value><![CDATA[SFTP]]></value>

<value><![CDATA[22]]></value>

</result>
</record_results>

<record_results>
<result>

<value><![CDATA[user]]></value>

<value><![CDATA[user]]></value>

<value><![CDATA[SSH]]></value>

<value><![CDATA[22]]></value>

</result>
</record_results>

<record_results/>
</info>

</appendix_info>

</target>

<target>
<ip>172.30.3.37</ip>
<host_score>5.0</host_score>

<vul_score>5.0</vul_score>


<config_score>0</config_score>







<vuln_scanned>

<vuln>
<port>22</port>
<vul_id>2012</vul_id>
<protocol>TCP</protocol>
<service>ssh</service>
<mess_string><![CDATA[ssh [sysadmin:root123]\nssh [test2:test]\nssh [test:admin]\nssh [admin:admin]\nssh [test123:password]]]></mess_string>
<vul_confirmed>False</vul_confirmed>
<has_result>-1</has_result>


</vuln>

<vuln>
<port>22</port>
<vul_id>2057</vul_id>
<protocol>TCP</protocol>
<service>ssh</service>
<mess_string><![CDATA[sftp [sysadmin:root123]\nsftp [test2:test]\nsftp [test:admin]]]></mess_string>
<vul_confirmed>False</vul_confirmed>
<has_result>-1</has_result>


</vuln>

</vuln_scanned>



<vuln_detail>

<vuln>
<vul_id>2012</vul_id>
<plugin_id>2012</plugin_id>


<name>猜测出远程SSH服务存在用户名口令</name>

<threat_category>远程信息泄露</threat_category>
<cve_id></cve_id>
<nsfocus_id></nsfocus_id>
<bugtraq_id></bugtraq_id>
<cnnvd></cnnvd>
<cncve></cncve>
<date_found>2001-01-01</date_found>
<risk_points>5.0</risk_points>
<solution><![CDATA[建议您采取以下措施以降低威胁:

* 如果SSH服务不是必须的，建议停止此服务。

* 修改用户口令，设置足够强度的口令。]]></solution>

<description><![CDATA[本次扫描通过暴力猜测方式证实目标主机上的SSH服务存在可猜测的口令。

远程攻击者可通过猜测出的用户名口令对目标主机实施进一步的攻击，这将极大地威胁目标主机以及目标网络的安全。]]></description>
</vuln>

<vuln>
<vul_id>2057</vul_id>
<plugin_id>2057</plugin_id>


<name>猜测出sftp存在可登录的用户名口令</name>

<threat_category>远程信息泄露</threat_category>
<cve_id></cve_id>
<nsfocus_id></nsfocus_id>
<bugtraq_id></bugtraq_id>
<cnnvd></cnnvd>
<cncve></cncve>
<date_found>2021-05-24</date_found>
<risk_points>5.0</risk_points>
<solution><![CDATA[建议您采取以下措施以降低威胁:
修改用户口令:设置足够强度的口令。]]></solution>

<description><![CDATA[本次扫描通过暴力猜测方式证实sftp存在可登录的口令。远程攻击者可通过猜测出的用户名口令对目标主机实施进一步的攻击，这将极大地威胁目标主机以及目标网络的安全。]]></description>
</vuln>

</vuln_detail>





<password_results>

<password_result>
<type>SSH</type>
<username>test</username>
<password>admin</password>
</password_result>

<password_result>
<type>SFTP</type>
<username>sysadmin</username>
<password>root123</password>
</password_result>

<password_result>
<type>SSH</type>
<username>test123</username>
<password>password</password>
</password_result>

<password_result>
<type>SSH</type>
<username>sysadmin</username>
<password>root123</password>
</password_result>

<password_result>
<type>SSH</type>
<username>test2</username>
<password>test</password>
</password_result>

<password_result>
<type>SSH</type>
<username>admin</username>
<password>admin</password>
</password_result>

<password_result>
<type>SFTP</type>
<username>test2</username>
<password>test</password>
</password_result>

<password_result>
<type>SFTP</type>
<username>test</username>
<password>admin</password>
</password_result>

</password_results>


<appendix_info>

<info>
<info_name><![CDATA[操作系统类型]]></info_name>
<record_result_name>

<name><![CDATA[操作系统名字]]></name>

<name><![CDATA[版本号]]></name>

</record_result_name>

<record_results>
<result>

<value><![CDATA[linux:linux_kernel]]></value>

<value><![CDATA[]]></value>

</result>
</record_results>

<record_results/>
</info>

<info>
<info_name><![CDATA[端口Banner]]></info_name>
<record_result_name>

<name><![CDATA[端口]]></name>

<name><![CDATA[Banner]]></name>

</record_result_name>

<record_results>
<result>

<value><![CDATA[8435]]></value>

<value><![CDATA[Apache Tomcat/9.0.31]]></value>

</result>
</record_results>

<record_results>
<result>

<value><![CDATA[8982]]></value>

<value><![CDATA[jquery.js/3.5.1]]></value>

</result>
</record_results>

<record_results>
<result>

<value><![CDATA[8982]]></value>

<value><![CDATA[Apache Solr/8.8.1 apache]]></value>

</result>
</record_results>

<record_results>
<result>

<value><![CDATA[8982]]></value>

<value><![CDATA[Apache Solr]]></value>

</result>
</record_results>

<record_results>
<result>

<value><![CDATA[8445]]></value>

<value><![CDATA[Apache Tomcat/Coyote JSP engine/1.1]]></value>

</result>
</record_results>

<record_results>
<result>

<value><![CDATA[5984]]></value>

<value><![CDATA[CouchDB httpd/3.2.1]]></value>

</result>
</record_results>

<record_results>
<result>

<value><![CDATA[22]]></value>

<value><![CDATA[OpenSSH/7.4]]></value>

</result>
</record_results>

<record_results>
<result>

<value><![CDATA[8088]]></value>

<value><![CDATA[Jetty/9.4.51.v20230217]]></value>

</result>
</record_results>

<record_results>
<result>

<value><![CDATA[8089]]></value>

<value><![CDATA[jquery.js/4.8.1]]></value>

</result>
</record_results>

<record_results>
<result>

<value><![CDATA[8089]]></value>

<value><![CDATA[php/7.2.5 php]]></value>

</result>
</record_results>

<record_results>
<result>

<value><![CDATA[8089]]></value>

<value><![CDATA[phpMyAdmin/4.8.1 phpMyAdmin]]></value>

</result>
</record_results>

<record_results>
<result>

<value><![CDATA[8089]]></value>

<value><![CDATA[Apache httpd/2.4.25]]></value>

</result>
</record_results>

<record_results>
<result>

<value><![CDATA[9090]]></value>

<value><![CDATA[Web-Based Enterprise Management CIM serverOpenPegasus WBEM httpd]]></value>

</result>
</record_results>

<record_results>
<result>

<value><![CDATA[8889]]></value>

<value><![CDATA[Apache Druid/25.0.0 apache]]></value>

</result>
</record_results>

<record_results>
<result>

<value><![CDATA[4369]]></value>

<value><![CDATA[Erlang Port Mapper Daemon]]></value>

</result>
</record_results>

<record_results>
<result>

<value><![CDATA[8983]]></value>

<value><![CDATA[jquery.js/2.1.3]]></value>

</result>
</record_results>

<record_results>
<result>

<value><![CDATA[8983]]></value>

<value><![CDATA[Apache Solr/7.0.1 apache]]></value>

</result>
</record_results>

<record_results>
<result>

<value><![CDATA[8983]]></value>

<value><![CDATA[Apache Solr]]></value>

</result>
</record_results>

<record_results>
<result>

<value><![CDATA[8087]]></value>

<value><![CDATA[Apache Tomcat/Coyote JSP engine/1.1]]></value>

</result>
</record_results>

<record_results>
<result>

<value><![CDATA[8435]]></value>

<value><![CDATA[Tomcat/9.0.31]]></value>

</result>
</record_results>

<record_results>
<result>

<value><![CDATA[8445]]></value>

<value><![CDATA[Apache-Coyote/1.1]]></value>

</result>
</record_results>

<record_results/>
</info>

<info>
<info_name><![CDATA[远程端口信息]]></info_name>
<record_result_name>

<name><![CDATA[端口]]></name>

<name><![CDATA[协议]]></name>

<name><![CDATA[服务]]></name>

<name><![CDATA[状态]]></name>

</record_result_name>

<record_results>
<result>

<value><![CDATA[5006]]></value>

<value><![CDATA[tcp]]></value>

<value><![CDATA[wsm-server]]></value>

<value><![CDATA[open]]></value>

</result>
</record_results>

<record_results>
<result>

<value><![CDATA[22]]></value>

<value><![CDATA[tcp]]></value>

<value><![CDATA[ssh]]></value>

<value><![CDATA[open]]></value>

</result>
</record_results>

<record_results>
<result>

<value><![CDATA[8445]]></value>

<value><![CDATA[tcp]]></value>

<value><![CDATA[HTTPS]]></value>

<value><![CDATA[open]]></value>

</result>
</record_results>

<record_results>
<result>

<value><![CDATA[5984]]></value>

<value><![CDATA[tcp]]></value>

<value><![CDATA[http]]></value>

<value><![CDATA[open]]></value>

</result>
</record_results>

<record_results>
<result>

<value><![CDATA[8087-8089]]></value>

<value><![CDATA[tcp]]></value>

<value><![CDATA[http]]></value>

<value><![CDATA[open]]></value>

</result>
</record_results>

<record_results>
<result>

<value><![CDATA[8889]]></value>

<value><![CDATA[tcp]]></value>

<value><![CDATA[http]]></value>

<value><![CDATA[open]]></value>

</result>
</record_results>

<record_results>
<result>

<value><![CDATA[8982-8983]]></value>

<value><![CDATA[tcp]]></value>

<value><![CDATA[http]]></value>

<value><![CDATA[open]]></value>

</result>
</record_results>

<record_results>
<result>

<value><![CDATA[9090]]></value>

<value><![CDATA[tcp]]></value>

<value><![CDATA[http]]></value>

<value><![CDATA[open]]></value>

</result>
</record_results>

<record_results>
<result>

<value><![CDATA[9100]]></value>

<value><![CDATA[tcp]]></value>

<value><![CDATA[rmiregistry]]></value>

<value><![CDATA[open]]></value>

</result>
</record_results>

<record_results>
<result>

<value><![CDATA[8435]]></value>

<value><![CDATA[tcp]]></value>

<value><![CDATA[www]]></value>

<value><![CDATA[open]]></value>

</result>
</record_results>

<record_results>
<result>

<value><![CDATA[4369]]></value>

<value><![CDATA[tcp]]></value>

<value><![CDATA[epmd]]></value>

<value><![CDATA[open]]></value>

</result>
</record_results>

<record_results/>
</info>

<info>
<info_name><![CDATA[安装软件信息]]></info_name>
<record_result_name>

<name><![CDATA[软件名称]]></name>

<name><![CDATA[版本号]]></name>

</record_result_name>

<record_results>
<result>

<value><![CDATA[jquery.js]]></value>

<value><![CDATA[4.8.1]]></value>

</result>
</record_results>

<record_results>
<result>

<value><![CDATA[phpMyAdmin]]></value>

<value><![CDATA[4.8.1 phpMyAdmin]]></value>

</result>
</record_results>

<record_results>
<result>

<value><![CDATA[Erlang Port Mapper Daemon]]></value>

<value><![CDATA[]]></value>

</result>
</record_results>

<record_results>
<result>

<value><![CDATA[Web-Based Enterprise Management CIM serverOpenPegasus WBEM httpd]]></value>

<value><![CDATA[]]></value>

</result>
</record_results>

<record_results>
<result>

<value><![CDATA[Apache Druid]]></value>

<value><![CDATA[25.0.0 apache]]></value>

</result>
</record_results>

<record_results>
<result>

<value><![CDATA[OpenSSH]]></value>

<value><![CDATA[7.4]]></value>

</result>
</record_results>

<record_results>
<result>

<value><![CDATA[WWW]]></value>

<value><![CDATA[Apache-Coyote]]></value>

</result>
</record_results>

<record_results>
<result>

<value><![CDATA[Jetty]]></value>

<value><![CDATA[9.4.51.v20230217]]></value>

</result>
</record_results>

<record_results>
<result>

<value><![CDATA[Apache httpd]]></value>

<value><![CDATA[2.4.25]]></value>

</result>
</record_results>

<record_results>
<result>

<value><![CDATA[Apache Solr]]></value>

<value><![CDATA[7.0.1 apache]]></value>

</result>
</record_results>

<record_results>
<result>

<value><![CDATA[HTTPS]]></value>

<value><![CDATA[Apache-Coyote]]></value>

</result>
</record_results>

<record_results>
<result>

<value><![CDATA[Apache Tomcat]]></value>

<value><![CDATA[Coyote JSP engine/1.1]]></value>

</result>
</record_results>

<record_results>
<result>

<value><![CDATA[Tomcat]]></value>

<value><![CDATA[9.0.31]]></value>

</result>
</record_results>

<record_results>
<result>

<value><![CDATA[php]]></value>

<value><![CDATA[7.2.5 php]]></value>

</result>
</record_results>

<record_results>
<result>

<value><![CDATA[CouchDB httpd]]></value>

<value><![CDATA[3.2.1]]></value>

</result>
</record_results>

<record_results/>
</info>

<info>
<info_name><![CDATA[应用程序信息]]></info_name>
<record_result_name>

<name><![CDATA[用户名]]></name>

<name><![CDATA[口令]]></name>

<name><![CDATA[应用]]></name>

</record_result_name>

<record_results>
<result>

<value><![CDATA[test]]></value>

<value><![CDATA[admin]]></value>

<value><![CDATA[SSH]]></value>

<value><![CDATA[22]]></value>

</result>
</record_results>

<record_results>
<result>

<value><![CDATA[sysadmin]]></value>

<value><![CDATA[root123]]></value>

<value><![CDATA[SFTP]]></value>

<value><![CDATA[22]]></value>

</result>
</record_results>

<record_results>
<result>

<value><![CDATA[test123]]></value>

<value><![CDATA[password]]></value>

<value><![CDATA[SSH]]></value>

<value><![CDATA[22]]></value>

</result>
</record_results>

<record_results>
<result>

<value><![CDATA[sysadmin]]></value>

<value><![CDATA[root123]]></value>

<value><![CDATA[SSH]]></value>

<value><![CDATA[22]]></value>

</result>
</record_results>

<record_results>
<result>

<value><![CDATA[test2]]></value>

<value><![CDATA[test]]></value>

<value><![CDATA[SSH]]></value>

<value><![CDATA[22]]></value>

</result>
</record_results>

<record_results>
<result>

<value><![CDATA[admin]]></value>

<value><![CDATA[admin]]></value>

<value><![CDATA[SSH]]></value>

<value><![CDATA[22]]></value>

</result>
</record_results>

<record_results>
<result>

<value><![CDATA[test2]]></value>

<value><![CDATA[test]]></value>

<value><![CDATA[SFTP]]></value>

<value><![CDATA[22]]></value>

</result>
</record_results>

<record_results>
<result>

<value><![CDATA[test]]></value>

<value><![CDATA[admin]]></value>

<value><![CDATA[SFTP]]></value>

<value><![CDATA[22]]></value>

</result>
</record_results>

<record_results/>
</info>

</appendix_info>

</target>

<target>
<ip>172.30.3.38</ip>
<host_score>5.0</host_score>

<vul_score>5.0</vul_score>


<config_score>0</config_score>







<vuln_scanned>

<vuln>
<port>22</port>
<vul_id>2012</vul_id>
<protocol>TCP</protocol>
<service>ssh</service>
<mess_string><![CDATA[ssh [root:root123]]]></mess_string>
<vul_confirmed>False</vul_confirmed>
<has_result>-1</has_result>


</vuln>

<vuln>
<port>22</port>
<vul_id>2057</vul_id>
<protocol>TCP</protocol>
<service>ssh</service>
<mess_string><![CDATA[sftp [root:root123]]]></mess_string>
<vul_confirmed>False</vul_confirmed>
<has_result>-1</has_result>


</vuln>

</vuln_scanned>



<vuln_detail>

<vuln>
<vul_id>2012</vul_id>
<plugin_id>2012</plugin_id>


<name>猜测出远程SSH服务存在用户名口令</name>

<threat_category>远程信息泄露</threat_category>
<cve_id></cve_id>
<nsfocus_id></nsfocus_id>
<bugtraq_id></bugtraq_id>
<cnnvd></cnnvd>
<cncve></cncve>
<date_found>2001-01-01</date_found>
<risk_points>5.0</risk_points>
<solution><![CDATA[建议您采取以下措施以降低威胁:

* 如果SSH服务不是必须的，建议停止此服务。

* 修改用户口令，设置足够强度的口令。]]></solution>

<description><![CDATA[本次扫描通过暴力猜测方式证实目标主机上的SSH服务存在可猜测的口令。

远程攻击者可通过猜测出的用户名口令对目标主机实施进一步的攻击，这将极大地威胁目标主机以及目标网络的安全。]]></description>
</vuln>

<vuln>
<vul_id>2057</vul_id>
<plugin_id>2057</plugin_id>


<name>猜测出sftp存在可登录的用户名口令</name>

<threat_category>远程信息泄露</threat_category>
<cve_id></cve_id>
<nsfocus_id></nsfocus_id>
<bugtraq_id></bugtraq_id>
<cnnvd></cnnvd>
<cncve></cncve>
<date_found>2021-05-24</date_found>
<risk_points>5.0</risk_points>
<solution><![CDATA[建议您采取以下措施以降低威胁:
修改用户口令:设置足够强度的口令。]]></solution>

<description><![CDATA[本次扫描通过暴力猜测方式证实sftp存在可登录的口令。远程攻击者可通过猜测出的用户名口令对目标主机实施进一步的攻击，这将极大地威胁目标主机以及目标网络的安全。]]></description>
</vuln>

</vuln_detail>





<password_results>

<password_result>
<type>SSH</type>
<username>root</username>
<password>root123</password>
</password_result>

<password_result>
<type>SFTP</type>
<username>root</username>
<password>root123</password>
</password_result>

</password_results>


<appendix_info>

<info>
<info_name><![CDATA[操作系统类型]]></info_name>
<record_result_name>

<name><![CDATA[操作系统名字]]></name>

<name><![CDATA[版本号]]></name>

</record_result_name>

<record_results>
<result>

<value><![CDATA[$1]]></value>

<value><![CDATA[]]></value>

</result>
</record_results>

<record_results/>
</info>

<info>
<info_name><![CDATA[端口Banner]]></info_name>
<record_result_name>

<name><![CDATA[端口]]></name>

<name><![CDATA[Banner]]></name>

</record_result_name>

<record_results>
<result>

<value><![CDATA[8080]]></value>

<value><![CDATA[Apache Tomcat/7.0.76]]></value>

</result>
</record_results>

<record_results>
<result>

<value><![CDATA[8080]]></value>

<value><![CDATA[Apache Tomcat/Coyote JSP engine/1.1]]></value>

</result>
</record_results>

<record_results>
<result>

<value><![CDATA[8009]]></value>

<value><![CDATA[Apache Jserv]]></value>

</result>
</record_results>

<record_results>
<result>

<value><![CDATA[80]]></value>

<value><![CDATA[Apache httpd/2.4.6]]></value>

</result>
</record_results>

<record_results>
<result>

<value><![CDATA[3306]]></value>

<value><![CDATA[MySQL/5.5.60-MariaDB]]></value>

</result>
</record_results>

<record_results>
<result>

<value><![CDATA[22]]></value>

<value><![CDATA[OpenSSH/7.4]]></value>

</result>
</record_results>

<record_results>
<result>

<value><![CDATA[8080]]></value>

<value><![CDATA[Tomcat/7.0.76]]></value>

</result>
</record_results>

<record_results>
<result>

<value><![CDATA[3306]]></value>

<value><![CDATA[MariaDB Server MySQL/5.5.60-MariaDB]]></value>

</result>
</record_results>

<record_results/>
</info>

<info>
<info_name><![CDATA[远程端口信息]]></info_name>
<record_result_name>

<name><![CDATA[端口]]></name>

<name><![CDATA[协议]]></name>

<name><![CDATA[服务]]></name>

<name><![CDATA[状态]]></name>

</record_result_name>

<record_results>
<result>

<value><![CDATA[111]]></value>

<value><![CDATA[tcp]]></value>

<value><![CDATA[rpcbind]]></value>

<value><![CDATA[open]]></value>

</result>
</record_results>

<record_results>
<result>

<value><![CDATA[22]]></value>

<value><![CDATA[tcp]]></value>

<value><![CDATA[ssh]]></value>

<value><![CDATA[open]]></value>

</result>
</record_results>

<record_results>
<result>

<value><![CDATA[80]]></value>

<value><![CDATA[tcp]]></value>

<value><![CDATA[http]]></value>

<value><![CDATA[open]]></value>

</result>
</record_results>

<record_results>
<result>

<value><![CDATA[8080]]></value>

<value><![CDATA[tcp]]></value>

<value><![CDATA[www]]></value>

<value><![CDATA[open]]></value>

</result>
</record_results>

<record_results>
<result>

<value><![CDATA[8009]]></value>

<value><![CDATA[tcp]]></value>

<value><![CDATA[ajp13]]></value>

<value><![CDATA[open]]></value>

</result>
</record_results>

<record_results>
<result>

<value><![CDATA[3306]]></value>

<value><![CDATA[tcp]]></value>

<value><![CDATA[MariaDB]]></value>

<value><![CDATA[open]]></value>

</result>
</record_results>

<record_results/>
</info>

<info>
<info_name><![CDATA[安装软件信息]]></info_name>
<record_result_name>

<name><![CDATA[软件名称]]></name>

<name><![CDATA[版本号]]></name>

</record_result_name>

<record_results>
<result>

<value><![CDATA[WWW]]></value>

<value><![CDATA[Tomcat]]></value>

</result>
</record_results>

<record_results>
<result>

<value><![CDATA[Tomcat]]></value>

<value><![CDATA[7.0.76]]></value>

</result>
</record_results>

<record_results>
<result>

<value><![CDATA[OpenSSH]]></value>

<value><![CDATA[7.4]]></value>

</result>
</record_results>

<record_results>
<result>

<value><![CDATA[Apache Tomcat]]></value>

<value><![CDATA[7.0.76]]></value>

</result>
</record_results>

<record_results>
<result>

<value><![CDATA[Apache httpd]]></value>

<value><![CDATA[2.4.6]]></value>

</result>
</record_results>

<record_results>
<result>

<value><![CDATA[Apache Jserv]]></value>

<value><![CDATA[]]></value>

</result>
</record_results>

<record_results>
<result>

<value><![CDATA[MySQL]]></value>

<value><![CDATA[5.5.60-MariaDB]]></value>

</result>
</record_results>

<record_results>
<result>

<value><![CDATA[MariaDB]]></value>

<value><![CDATA[MySQL/5.5.60-MariaDB]]></value>

</result>
</record_results>

<record_results/>
</info>

<info>
<info_name><![CDATA[应用程序信息]]></info_name>
<record_result_name>

<name><![CDATA[用户名]]></name>

<name><![CDATA[口令]]></name>

<name><![CDATA[应用]]></name>

</record_result_name>

<record_results>
<result>

<value><![CDATA[root]]></value>

<value><![CDATA[root123]]></value>

<value><![CDATA[SSH]]></value>

<value><![CDATA[22]]></value>

</result>
</record_results>

<record_results>
<result>

<value><![CDATA[root]]></value>

<value><![CDATA[root123]]></value>

<value><![CDATA[SFTP]]></value>

<value><![CDATA[22]]></value>

</result>
</record_results>

<record_results/>
</info>

</appendix_info>

</target>

<target>
<ip>172.30.3.39</ip>
<host_score>0.0</host_score>

<vul_score>0</vul_score>


<config_score>0</config_score>







<vuln_scanned>

</vuln_scanned>



<vuln_detail>

</vuln_detail>





<password_results>

</password_results>


<appendix_info>

<info>
<info_name><![CDATA[端口Banner]]></info_name>
<record_result_name>

<name><![CDATA[端口]]></name>

<name><![CDATA[Banner]]></name>

</record_result_name>

<record_results>
<result>

<value><![CDATA[8888]]></value>

<value><![CDATA[nginx igor_sysoev]]></value>

</result>
</record_results>

<record_results>
<result>

<value><![CDATA[8080]]></value>

<value><![CDATA[Jenkins/2.138 jenkins]]></value>

</result>
</record_results>

<record_results>
<result>

<value><![CDATA[8080]]></value>

<value><![CDATA[Jetty/9.4.z-SNAPSHOT]]></value>

</result>
</record_results>

<record_results>
<result>

<value><![CDATA[50000]]></value>

<value><![CDATA[Jenkins httpd/2.138]]></value>

</result>
</record_results>

<record_results>
<result>

<value><![CDATA[22]]></value>

<value><![CDATA[OpenSSH/7.4]]></value>

</result>
</record_results>

<record_results/>
</info>

<info>
<info_name><![CDATA[远程端口信息]]></info_name>
<record_result_name>

<name><![CDATA[端口]]></name>

<name><![CDATA[协议]]></name>

<name><![CDATA[服务]]></name>

<name><![CDATA[状态]]></name>

</record_result_name>

<record_results>
<result>

<value><![CDATA[22]]></value>

<value><![CDATA[tcp]]></value>

<value><![CDATA[ssh]]></value>

<value><![CDATA[open]]></value>

</result>
</record_results>

<record_results>
<result>

<value><![CDATA[8080]]></value>

<value><![CDATA[tcp]]></value>

<value><![CDATA[http]]></value>

<value><![CDATA[open]]></value>

</result>
</record_results>

<record_results>
<result>

<value><![CDATA[8888]]></value>

<value><![CDATA[tcp]]></value>

<value><![CDATA[http]]></value>

<value><![CDATA[open]]></value>

</result>
</record_results>

<record_results>
<result>

<value><![CDATA[50000]]></value>

<value><![CDATA[tcp]]></value>

<value><![CDATA[http]]></value>

<value><![CDATA[open]]></value>

</result>
</record_results>

<record_results/>
</info>

<info>
<info_name><![CDATA[安装软件信息]]></info_name>
<record_result_name>

<name><![CDATA[软件名称]]></name>

<name><![CDATA[版本号]]></name>

</record_result_name>

<record_results>
<result>

<value><![CDATA[Jenkins]]></value>

<value><![CDATA[2.138 jenkins]]></value>

</result>
</record_results>

<record_results>
<result>

<value><![CDATA[Jenkins httpd]]></value>

<value><![CDATA[2.138]]></value>

</result>
</record_results>

<record_results>
<result>

<value><![CDATA[nginx igor_sysoev]]></value>

<value><![CDATA[]]></value>

</result>
</record_results>

<record_results>
<result>

<value><![CDATA[Jetty]]></value>

<value><![CDATA[9.4.z-SNAPSHOT]]></value>

</result>
</record_results>

<record_results>
<result>

<value><![CDATA[OpenSSH]]></value>

<value><![CDATA[7.4]]></value>

</result>
</record_results>

<record_results/>
</info>

</appendix_info>

</target>

<target>
<ip>172.30.3.40</ip>
<host_score>5.0</host_score>

<vul_score>5.0</vul_score>


<config_score>0</config_score>







<vuln_scanned>

<vuln>
<port>22</port>
<vul_id>2012</vul_id>
<protocol>TCP</protocol>
<service>ssh</service>
<mess_string><![CDATA[ssh [admin:admin]\nssh [test:test]]]></mess_string>
<vul_confirmed>False</vul_confirmed>
<has_result>-1</has_result>


</vuln>

<vuln>
<port>8161</port>
<vul_id>2054</vul_id>
<protocol>TCP</protocol>
<service>http</service>
<mess_string><![CDATA[activemq [admin:admin]\nactivemq [user:user]]]></mess_string>
<vul_confirmed>False</vul_confirmed>
<has_result>-1</has_result>


</vuln>

</vuln_scanned>



<vuln_detail>

<vuln>
<vul_id>2012</vul_id>
<plugin_id>2012</plugin_id>


<name>猜测出远程SSH服务存在用户名口令</name>

<threat_category>远程信息泄露</threat_category>
<cve_id></cve_id>
<nsfocus_id></nsfocus_id>
<bugtraq_id></bugtraq_id>
<cnnvd></cnnvd>
<cncve></cncve>
<date_found>2001-01-01</date_found>
<risk_points>5.0</risk_points>
<solution><![CDATA[建议您采取以下措施以降低威胁:

* 如果SSH服务不是必须的，建议停止此服务。

* 修改用户口令，设置足够强度的口令。]]></solution>

<description><![CDATA[本次扫描通过暴力猜测方式证实目标主机上的SSH服务存在可猜测的口令。

远程攻击者可通过猜测出的用户名口令对目标主机实施进一步的攻击，这将极大地威胁目标主机以及目标网络的安全。]]></description>
</vuln>

<vuln>
<vul_id>2054</vul_id>
<plugin_id>2054</plugin_id>


<name>猜测出ActiveMQ存在可登录的用户名口令</name>

<threat_category>远程信息泄露</threat_category>
<cve_id></cve_id>
<nsfocus_id></nsfocus_id>
<bugtraq_id></bugtraq_id>
<cnnvd></cnnvd>
<cncve></cncve>
<date_found>2021-05-24</date_found>
<risk_points>5.0</risk_points>
<solution><![CDATA[建议您采取以下措施以降低威胁:
修改用户口令:设置足够强度的口令。]]></solution>

<description><![CDATA[本次扫描通过暴力猜测方式证实ActiveMQ存在可登录的口令。远程攻击者可通过猜测出的用户名口令对目标主机实施进一步的攻击，这将极大地威胁目标主机以及目标网络的安全。]]></description>
</vuln>

</vuln_detail>





<password_results>

<password_result>
<type>SSH</type>
<username>admin</username>
<password>admin</password>
</password_result>

<password_result>
<type>SSH</type>
<username>test</username>
<password>test</password>
</password_result>

<password_result>
<type>ACTIVEMQ</type>
<username>user</username>
<password>user</password>
</password_result>

<password_result>
<type>ACTIVEMQ</type>
<username>admin</username>
<password>admin</password>
</password_result>

</password_results>


<appendix_info>

<info>
<info_name><![CDATA[端口Banner]]></info_name>
<record_result_name>

<name><![CDATA[端口]]></name>

<name><![CDATA[Banner]]></name>

</record_result_name>

<record_results>
<result>

<value><![CDATA[7001]]></value>

<value><![CDATA[Oracle WebLogic Server]]></value>

</result>
</record_results>

<record_results>
<result>

<value><![CDATA[8161]]></value>

<value><![CDATA[Jetty/8.1.16.v20140903]]></value>

</result>
</record_results>

<record_results>
<result>

<value><![CDATA[8089]]></value>

<value><![CDATA[Apache Tomcat/8.5.77]]></value>

</result>
</record_results>

<record_results>
<result>

<value><![CDATA[8085]]></value>

<value><![CDATA[Oracle GlassFish oracle]]></value>

</result>
</record_results>

<record_results>
<result>

<value><![CDATA[22]]></value>

<value><![CDATA[OpenSSH/7.4]]></value>

</result>
</record_results>

<record_results>
<result>

<value><![CDATA[8080]]></value>

<value><![CDATA[php/5.6.36 php]]></value>

</result>
</record_results>

<record_results>
<result>

<value><![CDATA[8080]]></value>

<value><![CDATA[Apache httpd/2.4.33]]></value>

</result>
</record_results>

<record_results>
<result>

<value><![CDATA[8443]]></value>

<value><![CDATA[Apache Tomcat/9.0.31]]></value>

</result>
</record_results>

<record_results>
<result>

<value><![CDATA[61616]]></value>

<value><![CDATA[ActiveMQ OpenWire transport/12]]></value>

</result>
</record_results>

<record_results>
<result>

<value><![CDATA[8443]]></value>

<value><![CDATA[Tomcat/9.0.31]]></value>

</result>
</record_results>

<record_results>
<result>

<value><![CDATA[8089]]></value>

<value><![CDATA[Tomcat/8.5.77]]></value>

</result>
</record_results>

<record_results/>
</info>

<info>
<info_name><![CDATA[远程端口信息]]></info_name>
<record_result_name>

<name><![CDATA[端口]]></name>

<name><![CDATA[协议]]></name>

<name><![CDATA[服务]]></name>

<name><![CDATA[状态]]></name>

</record_result_name>

<record_results>
<result>

<value><![CDATA[4848]]></value>

<value><![CDATA[tcp]]></value>

<value><![CDATA[appserv-http]]></value>

<value><![CDATA[open]]></value>

</result>
</record_results>

<record_results>
<result>

<value><![CDATA[22]]></value>

<value><![CDATA[tcp]]></value>

<value><![CDATA[ssh]]></value>

<value><![CDATA[open]]></value>

</result>
</record_results>

<record_results>
<result>

<value><![CDATA[61616]]></value>

<value><![CDATA[tcp]]></value>

<value><![CDATA[apachemq]]></value>

<value><![CDATA[open]]></value>

</result>
</record_results>

<record_results>
<result>

<value><![CDATA[5005]]></value>

<value><![CDATA[tcp]]></value>

<value><![CDATA[https]]></value>

<value><![CDATA[open]]></value>

</result>
</record_results>

<record_results>
<result>

<value><![CDATA[7001]]></value>

<value><![CDATA[tcp]]></value>

<value><![CDATA[http]]></value>

<value><![CDATA[open]]></value>

</result>
</record_results>

<record_results>
<result>

<value><![CDATA[8080-8081]]></value>

<value><![CDATA[tcp]]></value>

<value><![CDATA[http]]></value>

<value><![CDATA[open]]></value>

</result>
</record_results>

<record_results>
<result>

<value><![CDATA[8085]]></value>

<value><![CDATA[tcp]]></value>

<value><![CDATA[http]]></value>

<value><![CDATA[open]]></value>

</result>
</record_results>

<record_results>
<result>

<value><![CDATA[8161]]></value>

<value><![CDATA[tcp]]></value>

<value><![CDATA[http]]></value>

<value><![CDATA[open]]></value>

</result>
</record_results>

<record_results>
<result>

<value><![CDATA[8089]]></value>

<value><![CDATA[tcp]]></value>

<value><![CDATA[www]]></value>

<value><![CDATA[open]]></value>

</result>
</record_results>

<record_results>
<result>

<value><![CDATA[8443]]></value>

<value><![CDATA[tcp]]></value>

<value><![CDATA[www]]></value>

<value><![CDATA[open]]></value>

</result>
</record_results>

<record_results>
<result>

<value><![CDATA[6123]]></value>

<value><![CDATA[tcp]]></value>

<value><![CDATA[backup-express]]></value>

<value><![CDATA[open]]></value>

</result>
</record_results>

<record_results>
<result>

<value><![CDATA[7676]]></value>

<value><![CDATA[tcp]]></value>

<value><![CDATA[imqbrokerd]]></value>

<value><![CDATA[open]]></value>

</result>
</record_results>

<record_results/>
</info>

<info>
<info_name><![CDATA[安装软件信息]]></info_name>
<record_result_name>

<name><![CDATA[软件名称]]></name>

<name><![CDATA[版本号]]></name>

</record_result_name>

<record_results>
<result>

<value><![CDATA[WWW]]></value>

<value><![CDATA[Tomcat]]></value>

</result>
</record_results>

<record_results>
<result>

<value><![CDATA[Oracle GlassFish oracle]]></value>

<value><![CDATA[]]></value>

</result>
</record_results>

<record_results>
<result>

<value><![CDATA[Tomcat]]></value>

<value><![CDATA[8.5.77]]></value>

</result>
</record_results>

<record_results>
<result>

<value><![CDATA[OpenSSH]]></value>

<value><![CDATA[7.4]]></value>

</result>
</record_results>

<record_results>
<result>

<value><![CDATA[ActiveMQ OpenWire transport]]></value>

<value><![CDATA[12]]></value>

</result>
</record_results>

<record_results>
<result>

<value><![CDATA[Jetty]]></value>

<value><![CDATA[8.1.16.v20140903]]></value>

</result>
</record_results>

<record_results>
<result>

<value><![CDATA[Apache httpd]]></value>

<value><![CDATA[2.4.33]]></value>

</result>
</record_results>

<record_results>
<result>

<value><![CDATA[Apache Tomcat]]></value>

<value><![CDATA[9.0.31]]></value>

</result>
</record_results>

<record_results>
<result>

<value><![CDATA[Oracle WebLogic Server]]></value>

<value><![CDATA[]]></value>

</result>
</record_results>

<record_results>
<result>

<value><![CDATA[php]]></value>

<value><![CDATA[5.6.36 php]]></value>

</result>
</record_results>

<record_results/>
</info>

<info>
<info_name><![CDATA[应用程序信息]]></info_name>
<record_result_name>

<name><![CDATA[用户名]]></name>

<name><![CDATA[口令]]></name>

<name><![CDATA[应用]]></name>

</record_result_name>

<record_results>
<result>

<value><![CDATA[admin]]></value>

<value><![CDATA[admin]]></value>

<value><![CDATA[SSH]]></value>

<value><![CDATA[22]]></value>

</result>
</record_results>

<record_results>
<result>

<value><![CDATA[test]]></value>

<value><![CDATA[test]]></value>

<value><![CDATA[SSH]]></value>

<value><![CDATA[22]]></value>

</result>
</record_results>

<record_results>
<result>

<value><![CDATA[user]]></value>

<value><![CDATA[user]]></value>

<value><![CDATA[ACTIVEMQ]]></value>

<value><![CDATA[8161]]></value>

</result>
</record_results>

<record_results>
<result>

<value><![CDATA[admin]]></value>

<value><![CDATA[admin]]></value>

<value><![CDATA[ACTIVEMQ]]></value>

<value><![CDATA[8161]]></value>

</result>
</record_results>

<record_results/>
</info>

</appendix_info>

</target>

</targets>
</report>
    </data>
</aurora>